missingrepo/Missing.py
missingrepo/__init__.py
missingrepo/repository/MissingRepository.py
missingrepo/repository/__init__.py
missingrepo/repository/serialize/__init__.py
missingrepo/repository/serialize/missing_deserializer.py
missingrepo/repository/serialize/missing_serializer.py
persuader_technology_automata_missing_repository-0.2.1.dist-info/LICENSE
persuader_technology_automata_missing_repository-0.2.1.dist-info/METADATA
persuader_technology_automata_missing_repository-0.2.1.dist-info/WHEEL
persuader_technology_automata_missing_repository-0.2.1.dist-info/top_level.txt
persuader_technology_automata_missing_repository-0.2.1.dist-info/RECORD
